{
"meta":{"test_sets":[],"test_metrics":[],"learn_metrics":[{"best_value":"Min","name":"RMSE"}],"launch_mode":"Train","parameters":"","iteration_count":521,"learn_sets":["learn"],"name":"experiment"},
"iterations":[
{"learn":[4514.367988],"iteration":0,"passed_time":0.02083151731,"remaining_time":10.832389},
{"learn":[4396.075004],"iteration":1,"passed_time":0.04079170427,"remaining_time":10.58544726},
{"learn":[4282.98311],"iteration":2,"passed_time":0.06042675737,"remaining_time":10.43368677},
{"learn":[4174.79939],"iteration":3,"passed_time":0.07609009333,"remaining_time":9.834644562},
{"learn":[4070.675726],"iteration":4,"passed_time":0.09289543283,"remaining_time":9.586808669},
{"learn":[3970.920809],"iteration":5,"passed_time":0.110010226,"remaining_time":9.4425444},
{"learn":[3875.923586],"iteration":6,"passed_time":0.1257523629,"remaining_time":9.233816362},
{"learn":[3784.241284],"iteration":7,"passed_time":0.1414356591,"remaining_time":9.069561639},
{"learn":[3696.437782],"iteration":8,"passed_time":0.1574947997,"remaining_time":8.959704163},
{"learn":[3612.433327],"iteration":9,"passed_time":0.1747546346,"remaining_time":8.929961831},
{"learn":[3531.40536],"iteration":10,"passed_time":0.1912634706,"remaining_time":8.867670002},
{"learn":[3454.365128],"iteration":11,"passed_time":0.2076124747,"remaining_time":8.806229136},
{"learn":[3379.874348],"iteration":12,"passed_time":0.2240947104,"remaining_time":8.75693176},
{"learn":[3308.528335],"iteration":13,"passed_time":0.2398402773,"remaining_time":8.685644329},
{"learn":[3240.498263],"iteration":14,"passed_time":0.2562579922,"remaining_time":8.644436272},
{"learn":[3175.554207],"iteration":15,"passed_time":0.2720049592,"remaining_time":8.585156524},
{"learn":[3112.776394],"iteration":16,"passed_time":0.2904876486,"remaining_time":8.612104406},
{"learn":[3051.982649],"iteration":17,"passed_time":0.3071633466,"remaining_time":8.583509074},
{"learn":[2995.320038],"iteration":18,"passed_time":0.3226584605,"remaining_time":8.524976168},
{"learn":[2940.916756],"iteration":19,"passed_time":0.3397227131,"remaining_time":8.510053964},
{"learn":[2888.492392],"iteration":20,"passed_time":0.3549126634,"remaining_time":8.450301511},
{"learn":[2837.334694],"iteration":21,"passed_time":0.369871611,"remaining_time":8.389360632},
{"learn":[2789.066325],"iteration":22,"passed_time":0.3856704586,"remaining_time":8.350603843},
{"learn":[2742.431923],"iteration":23,"passed_time":0.401199563,"remaining_time":8.308174283},
{"learn":[2698.95566],"iteration":24,"passed_time":0.416451524,"remaining_time":8.262398237},
{"learn":[2656.632764],"iteration":25,"passed_time":0.4317964462,"remaining_time":8.220740033},
{"learn":[2616.598576],"iteration":26,"passed_time":0.4462134273,"remaining_time":8.164053078},
{"learn":[2578.704812],"iteration":27,"passed_time":0.4600035711,"remaining_time":8.099348591},
{"learn":[2540.404783],"iteration":28,"passed_time":0.4729644149,"remaining_time":8.024085936},
{"learn":[2505.028012],"iteration":29,"passed_time":0.4858278276,"remaining_time":7.951382112},
{"learn":[2471.561509],"iteration":30,"passed_time":0.4984178871,"remaining_time":7.878218216},
{"learn":[2439.585523],"iteration":31,"passed_time":0.5114954524,"remaining_time":7.816289881},
{"learn":[2406.799528],"iteration":32,"passed_time":0.5247160093,"remaining_time":7.759436744},
{"learn":[2376.121155],"iteration":33,"passed_time":0.5388117367,"remaining_time":7.717685757},
{"learn":[2346.670074],"iteration":34,"passed_time":0.5525550698,"remaining_time":7.672621827},
{"learn":[2319.433463],"iteration":35,"passed_time":0.5670967625,"remaining_time":7.640053605},
{"learn":[2293.262063],"iteration":36,"passed_time":0.5805882726,"remaining_time":7.594722269},
{"learn":[2269.22217],"iteration":37,"passed_time":0.5942097443,"remaining_time":7.552718592},
{"learn":[2246.219365],"iteration":38,"passed_time":0.6073684405,"remaining_time":7.506450983},
{"learn":[2223.566147],"iteration":39,"passed_time":0.6206236679,"remaining_time":7.462999607},
{"learn":[2200.674869],"iteration":40,"passed_time":0.6345175429,"remaining_time":7.428498063},
{"learn":[2179.505174],"iteration":41,"passed_time":0.6485386293,"remaining_time":7.396428653},
{"learn":[2159.562467],"iteration":42,"passed_time":0.662155191,"remaining_time":7.36070189},
{"learn":[2140.257168],"iteration":43,"passed_time":0.6761756474,"remaining_time":7.330358723},
{"learn":[2121.547511],"iteration":44,"passed_time":0.6899632111,"remaining_time":7.298277522},
{"learn":[2104.047802],"iteration":45,"passed_time":0.7036439735,"remaining_time":7.265888857},
{"learn":[2086.929407],"iteration":46,"passed_time":0.7180642447,"remaining_time":7.241754298},
{"learn":[2071.11392],"iteration":47,"passed_time":0.7316861264,"remaining_time":7.210157037},
{"learn":[2055.653759],"iteration":48,"passed_time":0.744878993,"remaining_time":7.175160913},
{"learn":[2041.098351],"iteration":49,"passed_time":0.7581226803,"remaining_time":7.141515648},
{"learn":[2027.598942],"iteration":50,"passed_time":0.7717184617,"remaining_time":7.111915235},
{"learn":[2014.362224],"iteration":51,"passed_time":0.7857015777,"remaining_time":7.086423845},
{"learn":[2001.878249],"iteration":52,"passed_time":0.8001932197,"remaining_time":7.06585711},
{"learn":[1988.623102],"iteration":53,"passed_time":0.8148575238,"remaining_time":7.047008586},
{"learn":[1976.219943],"iteration":54,"passed_time":0.8292256944,"remaining_time":7.025803156},
{"learn":[1965.478306],"iteration":55,"passed_time":0.8426223534,"remaining_time":6.996774899},
{"learn":[1955.237736],"iteration":56,"passed_time":0.8568781827,"remaining_time":6.975289066},
{"learn":[1944.652683],"iteration":57,"passed_time":0.8708626587,"remaining_time":6.951886396},
{"learn":[1934.70688],"iteration":58,"passed_time":0.8842059771,"remaining_time":6.923782397},
{"learn":[1925.637791],"iteration":59,"passed_time":0.8985007368,"remaining_time":6.903480661},
{"learn":[1916.664334],"iteration":60,"passed_time":0.9124849028,"remaining_time":6.881033693},
{"learn":[1908.04099],"iteration":61,"passed_time":0.927918486,"remaining_time":6.869590082},
{"learn":[1899.45199],"iteration":62,"passed_time":0.9466889189,"remaining_time":6.882278172},
{"learn":[1890.718812],"iteration":63,"passed_time":0.9696155611,"remaining_time":6.923661116},
{"learn":[1883.376807],"iteration":64,"passed_time":0.9885016353,"remaining_time":6.934719164},
{"learn":[1875.910956],"iteration":65,"passed_time":1.005273504,"remaining_time":6.930294614},
{"learn":[1868.396882],"iteration":66,"passed_time":1.019569714,"remaining_time":6.908726122},
{"learn":[1861.723418],"iteration":67,"passed_time":1.033810843,"remaining_time":6.887004588},
{"learn":[1855.216236],"iteration":68,"passed_time":1.047376004,"remaining_time":6.861071796},
{"learn":[1848.87712],"iteration":69,"passed_time":1.061253669,"remaining_time":6.837505782},
{"learn":[1842.630572],"iteration":70,"passed_time":1.074682918,"remaining_time":6.81137061},
{"learn":[1836.726428],"iteration":71,"passed_time":1.088587863,"remaining_time":6.788554871},
{"learn":[1831.657298],"iteration":72,"passed_time":1.10176148,"remaining_time":6.761495109},
{"learn":[1826.183965],"iteration":73,"passed_time":1.115730806,"remaining_time":6.739617164},
{"learn":[1821.162338],"iteration":74,"passed_time":1.129433858,"remaining_time":6.716366678},
{"learn":[1815.852315],"iteration":75,"passed_time":1.14387747,"remaining_time":6.697703606},
{"learn":[1810.846995],"iteration":76,"passed_time":1.156896124,"remaining_time":6.670933497},
{"learn":[1805.98108],"iteration":77,"passed_time":1.170370204,"remaining_time":6.647102571},
{"learn":[1800.9377],"iteration":78,"passed_time":1.183928265,"remaining_time":6.624003712},
{"learn":[1796.942546],"iteration":79,"passed_time":1.1977851,"remaining_time":6.602790363},
{"learn":[1792.324152],"iteration":80,"passed_time":1.21209556,"remaining_time":6.584222794},
{"learn":[1787.883469],"iteration":81,"passed_time":1.225936254,"remaining_time":6.563244092},
{"learn":[1784.443568],"iteration":82,"passed_time":1.239639787,"remaining_time":6.541713573},
{"learn":[1780.848414],"iteration":83,"passed_time":1.252691642,"remaining_time":6.516979136},
{"learn":[1777.554973],"iteration":84,"passed_time":1.265823088,"remaining_time":6.492927837},
{"learn":[1774.227948],"iteration":85,"passed_time":1.278803512,"remaining_time":6.4683666},
{"learn":[1770.687181],"iteration":86,"passed_time":1.292656886,"remaining_time":6.448426306},
{"learn":[1767.446585],"iteration":87,"passed_time":1.307726215,"remaining_time":6.434607399},
{"learn":[1764.674174],"iteration":88,"passed_time":1.320842281,"remaining_time":6.411279385},
{"learn":[1761.606998],"iteration":89,"passed_time":1.334684145,"remaining_time":6.391654073},
{"learn":[1758.252177],"iteration":90,"passed_time":1.348874714,"remaining_time":6.373803592},
{"learn":[1755.312494],"iteration":91,"passed_time":1.36208132,"remaining_time":6.351444418},
{"learn":[1752.125294],"iteration":92,"passed_time":1.375273487,"remaining_time":6.329215617},
{"learn":[1749.412717],"iteration":93,"passed_time":1.388737727,"remaining_time":6.308414993},
{"learn":[1746.313033],"iteration":94,"passed_time":1.402777383,"remaining_time":6.290349109},
{"learn":[1744.043953],"iteration":95,"passed_time":1.416624998,"remaining_time":6.271516918},
{"learn":[1740.672972],"iteration":96,"passed_time":1.430477162,"remaining_time":6.25280739},
{"learn":[1738.377742],"iteration":97,"passed_time":1.444125894,"remaining_time":6.233318911},
{"learn":[1736.148705],"iteration":98,"passed_time":1.457681975,"remaining_time":6.21355347},
{"learn":[1734.111781],"iteration":99,"passed_time":1.47156718,"remaining_time":6.195297828},
{"learn":[1731.893049],"iteration":100,"passed_time":1.485342594,"remaining_time":6.176672172},
{"learn":[1730.078868],"iteration":101,"passed_time":1.498434649,"remaining_time":6.15533449},
{"learn":[1727.809192],"iteration":102,"passed_time":1.511501954,"remaining_time":6.134056474},
{"learn":[1725.830286],"iteration":103,"passed_time":1.524483048,"remaining_time":6.112590684},
{"learn":[1722.971544],"iteration":104,"passed_time":1.538269652,"remaining_time":6.094477859},
{"learn":[1721.407931],"iteration":105,"passed_time":1.551665951,"remaining_time":6.074918582},
{"learn":[1719.63233],"iteration":106,"passed_time":1.564312711,"remaining_time":6.052574415},
{"learn":[1717.828425],"iteration":107,"passed_time":1.578339198,"remaining_time":6.035686006},
{"learn":[1716.340183],"iteration":108,"passed_time":1.592140362,"remaining_time":6.017998431},
{"learn":[1714.550204],"iteration":109,"passed_time":1.606142428,"remaining_time":6.001132162},
{"learn":[1712.298378],"iteration":110,"passed_time":1.620119354,"remaining_time":5.98422464},
{"learn":[1710.65449],"iteration":111,"passed_time":1.633506593,"remaining_time":5.965216039},
{"learn":[1708.5551],"iteration":112,"passed_time":1.646510667,"remaining_time":5.94492347},
{"learn":[1706.997717],"iteration":113,"passed_time":1.660700065,"remaining_time":5.928990585},
{"learn":[1705.627314],"iteration":114,"passed_time":1.674289757,"remaining_time":5.910970794},
{"learn":[1703.67764],"iteration":115,"passed_time":1.687972999,"remaining_time":5.893354006},
{"learn":[1702.180229],"iteration":116,"passed_time":1.702505112,"remaining_time":5.8787356},
{"learn":[1700.236749],"iteration":117,"passed_time":1.715788219,"remaining_time":5.859852987},
{"learn":[1698.463759],"iteration":118,"passed_time":1.730360842,"remaining_time":5.845420661},
{"learn":[1697.130917],"iteration":119,"passed_time":1.744623172,"remaining_time":5.829949099},
{"learn":[1695.779921],"iteration":120,"passed_time":1.758517137,"remaining_time":5.813279791},
{"learn":[1694.265236],"iteration":121,"passed_time":1.772652775,"remaining_time":5.797446369},
{"learn":[1693.032506],"iteration":122,"passed_time":1.786680211,"remaining_time":5.781290439},
{"learn":[1691.498037],"iteration":123,"passed_time":1.800169781,"remaining_time":5.7634468},
{"learn":[1689.777832],"iteration":124,"passed_time":1.81351389,"remaining_time":5.745212002},
{"learn":[1688.193271],"iteration":125,"passed_time":1.827342064,"remaining_time":5.728572343},
{"learn":[1687.017392],"iteration":126,"passed_time":1.840830724,"remaining_time":5.710923663},
{"learn":[1685.510378],"iteration":127,"passed_time":1.854546857,"remaining_time":5.694038396},
{"learn":[1683.971813],"iteration":128,"passed_time":1.869017749,"remaining_time":5.679495794},
{"learn":[1682.532348],"iteration":129,"passed_time":1.883202897,"remaining_time":5.664094867},
{"learn":[1681.549204],"iteration":130,"passed_time":1.89696832,"remaining_time":5.647462939},
{"learn":[1680.592075],"iteration":131,"passed_time":1.91040275,"remaining_time":5.629899013},
{"learn":[1679.558945],"iteration":132,"passed_time":1.924599148,"remaining_time":5.614620072},
{"learn":[1678.228379],"iteration":133,"passed_time":1.938738456,"remaining_time":5.599192407},
{"learn":[1677.076526],"iteration":134,"passed_time":1.95251932,"remaining_time":5.582758944},
{"learn":[1675.814957],"iteration":135,"passed_time":1.966891151,"remaining_time":5.568037448},
{"learn":[1674.824185],"iteration":136,"passed_time":1.980774525,"remaining_time":5.551951954},
{"learn":[1674.056663],"iteration":137,"passed_time":1.994301756,"remaining_time":5.534909946},
{"learn":[1672.891966],"iteration":138,"passed_time":2.008453584,"remaining_time":5.519635029},
{"learn":[1671.927486],"iteration":139,"passed_time":2.021949554,"remaining_time":5.502591287},
{"learn":[1670.706618],"iteration":140,"passed_time":2.035747648,"remaining_time":5.486412101},
{"learn":[1669.668975],"iteration":141,"passed_time":2.048693482,"remaining_time":5.467991757},
{"learn":[1668.541667],"iteration":142,"passed_time":2.063150453,"remaining_time":5.453642457},
{"learn":[1667.720592],"iteration":143,"passed_time":2.076458271,"remaining_time":5.436283113},
{"learn":[1666.569076],"iteration":144,"passed_time":2.09070694,"remaining_time":5.421419377},
{"learn":[1665.608253],"iteration":145,"passed_time":2.103858357,"remaining_time":5.403745779},
{"learn":[1664.599814],"iteration":146,"passed_time":2.117078754,"remaining_time":5.38630921},
{"learn":[1663.273533],"iteration":147,"passed_time":2.130707015,"remaining_time":5.369957545},
{"learn":[1662.404769],"iteration":148,"passed_time":2.144109474,"remaining_time":5.353078688},
{"learn":[1661.373515],"iteration":149,"passed_time":2.157418232,"remaining_time":5.336014428},
{"learn":[1660.576986],"iteration":150,"passed_time":2.171786433,"remaining_time":5.321595895},
{"learn":[1659.732194],"iteration":151,"passed_time":2.186216254,"remaining_time":5.307327617},
{"learn":[1658.979152],"iteration":152,"passed_time":2.200787497,"remaining_time":5.293397379},
{"learn":[1657.815688],"iteration":153,"passed_time":2.214114485,"remaining_time":5.276493612},
{"learn":[1657.067122],"iteration":154,"passed_time":2.227787648,"remaining_time":5.260453414},
{"learn":[1656.145124],"iteration":155,"passed_time":2.241049905,"remaining_time":5.24348215},
{"learn":[1655.293515],"iteration":156,"passed_time":2.254683917,"remaining_time":5.227420037},
{"learn":[1654.050018],"iteration":157,"passed_time":2.267870074,"remaining_time":5.210359726},
{"learn":[1653.304822],"iteration":158,"passed_time":2.280846948,"remaining_time":5.192871667},
{"learn":[1652.467322],"iteration":159,"passed_time":2.294434529,"remaining_time":5.176817906},
{"learn":[1651.716164],"iteration":160,"passed_time":2.308144152,"remaining_time":5.161067669},
{"learn":[1650.861256],"iteration":161,"passed_time":2.321324498,"remaining_time":5.144169721},
{"learn":[1649.76546],"iteration":162,"passed_time":2.335564367,"remaining_time":5.129644439},
{"learn":[1648.875344],"iteration":163,"passed_time":2.348969846,"remaining_time":5.113306312},
{"learn":[1648.218499],"iteration":164,"passed_time":2.362170073,"remaining_time":5.096560885},
{"learn":[1647.279683],"iteration":165,"passed_time":2.376280331,"remaining_time":5.081804322},
{"learn":[1646.425563],"iteration":166,"passed_time":2.390356258,"remaining_time":5.066982726},
{"learn":[1645.721083],"iteration":167,"passed_time":2.404398254,"remaining_time":5.052098713},
{"learn":[1645.074559],"iteration":168,"passed_time":2.419609155,"remaining_time":5.039659305},
{"learn":[1644.303526],"iteration":169,"passed_time":2.433059185,"remaining_time":5.023551611},
{"learn":[1643.643878],"iteration":170,"passed_time":2.446734187,"remaining_time":5.007935471},
{"learn":[1642.831078],"iteration":171,"passed_time":2.460214737,"remaining_time":4.991947345},
{"learn":[1642.170733],"iteration":172,"passed_time":2.474421576,"remaining_time":4.977449181},
{"learn":[1641.387868],"iteration":173,"passed_time":2.488310261,"remaining_time":4.962319888},
{"learn":[1640.625624],"iteration":174,"passed_time":2.502367928,"remaining_time":4.947538874},
{"learn":[1639.907656],"iteration":175,"passed_time":2.517039752,"remaining_time":4.933969968},
{"learn":[1639.223503],"iteration":176,"passed_time":2.531298981,"remaining_time":4.91958672},
{"learn":[1638.667975],"iteration":177,"passed_time":2.545151515,"remaining_time":4.904421179},
{"learn":[1637.870626],"iteration":178,"passed_time":2.559919871,"remaining_time":4.891020088},
{"learn":[1637.129716],"iteration":179,"passed_time":2.574529974,"remaining_time":4.877304007},
{"learn":[1636.285076],"iteration":180,"passed_time":2.589452501,"remaining_time":4.86416492},
{"learn":[1635.44817],"iteration":181,"passed_time":2.604419339,"remaining_time":4.851088769},
{"learn":[1634.86551],"iteration":182,"passed_time":2.61967903,"remaining_time":4.838532854},
{"learn":[1634.219095],"iteration":183,"passed_time":2.633653156,"remaining_time":4.823593009},
{"learn":[1633.644451],"iteration":184,"passed_time":2.648177369,"remaining_time":4.80966268},
{"learn":[1632.629697],"iteration":185,"passed_time":2.663545091,"remaining_time":4.797245191},
{"learn":[1631.90297],"iteration":186,"passed_time":2.678924154,"remaining_time":4.784816403},
{"learn":[1631.161004],"iteration":187,"passed_time":2.693144462,"remaining_time":4.770303755},
{"learn":[1630.225918],"iteration":188,"passed_time":2.708846519,"remaining_time":4.75839706},
{"learn":[1629.699925],"iteration":189,"passed_time":2.722645583,"remaining_time":4.743135199},
{"learn":[1629.12703],"iteration":190,"passed_time":2.736595038,"remaining_time":4.728148495},
{"learn":[1628.677457],"iteration":191,"passed_time":2.750847187,"remaining_time":4.713691274},
{"learn":[1628.02359],"iteration":192,"passed_time":2.765592113,"remaining_time":4.700073642},
{"learn":[1627.280014],"iteration":193,"passed_time":2.780033614,"remaining_time":4.685932947},
{"learn":[1626.616964],"iteration":194,"passed_time":2.79487053,"remaining_time":4.67245022},
{"learn":[1626.174558],"iteration":195,"passed_time":2.808459871,"remaining_time":4.656884991},
{"learn":[1625.470756],"iteration":196,"passed_time":2.823191386,"remaining_time":4.643218321},
{"learn":[1624.794624],"iteration":197,"passed_time":2.837895711,"remaining_time":4.629496538},
{"learn":[1624.055938],"iteration":198,"passed_time":2.850894885,"remaining_time":4.613005794},
{"learn":[1623.222055],"iteration":199,"passed_time":2.863776428,"remaining_time":4.596361167},
{"learn":[1622.641791],"iteration":200,"passed_time":2.877571102,"remaining_time":4.581207724},
{"learn":[1622.100732],"iteration":201,"passed_time":2.891182233,"remaining_time":4.565777884},
{"learn":[1621.476518],"iteration":202,"passed_time":2.904217758,"remaining_time":4.549464272},
{"learn":[1620.908213],"iteration":203,"passed_time":2.91785227,"remaining_time":4.534113577},
{"learn":[1620.310592],"iteration":204,"passed_time":2.930972236,"remaining_time":4.517986471},
{"learn":[1619.886603],"iteration":205,"passed_time":2.944305204,"remaining_time":4.502214268},
{"learn":[1619.160183],"iteration":206,"passed_time":2.958049057,"remaining_time":4.487088908},
{"learn":[1618.656244],"iteration":207,"passed_time":2.971634579,"remaining_time":4.471738573},
{"learn":[1618.149344],"iteration":208,"passed_time":2.984909786,"remaining_time":4.455941882},
{"learn":[1617.577875],"iteration":209,"passed_time":2.998254785,"remaining_time":4.440272562},
{"learn":[1617.039624],"iteration":210,"passed_time":3.011993838,"remaining_time":4.425204217},
{"learn":[1616.610865],"iteration":211,"passed_time":3.025919063,"remaining_time":4.410419766},
{"learn":[1616.011051],"iteration":212,"passed_time":3.039718947,"remaining_time":4.395462139},
{"learn":[1615.54693],"iteration":213,"passed_time":3.05426688,"remaining_time":4.381588467},
{"learn":[1614.961491],"iteration":214,"passed_time":3.067607388,"remaining_time":4.36599005},
{"learn":[1614.546955],"iteration":215,"passed_time":3.080539231,"remaining_time":4.349835489},
{"learn":[1613.953717],"iteration":216,"passed_time":3.094525508,"remaining_time":4.335187808},
{"learn":[1613.418338],"iteration":217,"passed_time":3.107819925,"remaining_time":4.319584575},
{"learn":[1612.254398],"iteration":218,"passed_time":3.122284557,"remaining_time":4.305616147},
{"learn":[1611.659061],"iteration":219,"passed_time":3.135533964,"remaining_time":4.28998056},
{"learn":[1611.054369],"iteration":220,"passed_time":3.148942714,"remaining_time":4.274582869},
{"learn":[1610.381097],"iteration":221,"passed_time":3.162198041,"remaining_time":4.258996461},
{"learn":[1609.740636],"iteration":222,"passed_time":3.176084476,"remaining_time":4.244274322},
{"learn":[1609.344915],"iteration":223,"passed_time":3.189483545,"remaining_time":4.22891345},
{"learn":[1608.907376],"iteration":224,"passed_time":3.202693432,"remaining_time":4.213321137},
{"learn":[1608.29229],"iteration":225,"passed_time":3.215842978,"remaining_time":4.197671144},
{"learn":[1607.723105],"iteration":226,"passed_time":3.229157766,"remaining_time":4.182257195},
{"learn":[1607.257246],"iteration":227,"passed_time":3.242428873,"remaining_time":4.166805526},
{"learn":[1606.76674],"iteration":228,"passed_time":3.256031505,"remaining_time":4.151795631},
{"learn":[1606.285793],"iteration":229,"passed_time":3.269787718,"remaining_time":4.136992287},
{"learn":[1605.880162],"iteration":230,"passed_time":3.283733144,"remaining_time":4.122435548},
{"learn":[1605.266646],"iteration":231,"passed_time":3.297298215,"remaining_time":4.107410276},
{"learn":[1604.665305],"iteration":232,"passed_time":3.31040002,"remaining_time":4.091824918},
{"learn":[1604.161508],"iteration":233,"passed_time":3.323782629,"remaining_time":4.076605191},
{"learn":[1603.682095],"iteration":234,"passed_time":3.336979396,"remaining_time":4.061174924},
{"learn":[1603.313218],"iteration":235,"passed_time":3.351544189,"remaining_time":4.047415652},
{"learn":[1602.63657],"iteration":236,"passed_time":3.366316364,"remaining_time":4.03389809},
{"learn":[1602.164424],"iteration":237,"passed_time":3.379731513,"remaining_time":4.018756379},
{"learn":[1601.4014],"iteration":238,"passed_time":3.394755732,"remaining_time":4.005527684},
{"learn":[1600.893668],"iteration":239,"passed_time":3.407472323,"remaining_time":3.989582178},
{"learn":[1600.440948],"iteration":240,"passed_time":3.420239644,"remaining_time":3.973722408},
{"learn":[1599.491143],"iteration":241,"passed_time":3.433608913,"remaining_time":3.958582177},
{"learn":[1598.981134],"iteration":242,"passed_time":3.44852187,"remaining_time":3.945222551},
{"learn":[1598.436915],"iteration":243,"passed_time":3.46286003,"remaining_time":3.931197657},
{"learn":[1598.023905],"iteration":244,"passed_time":3.476904917,"remaining_time":3.916839825},
{"learn":[1597.503066],"iteration":245,"passed_time":3.490569159,"remaining_time":3.90205902},
{"learn":[1597.198708],"iteration":246,"passed_time":3.504356613,"remaining_time":3.887423935},
{"learn":[1596.900787],"iteration":247,"passed_time":3.518539851,"remaining_time":3.873231369},
{"learn":[1596.552121],"iteration":248,"passed_time":3.533126335,"remaining_time":3.859479369},
{"learn":[1596.061555],"iteration":249,"passed_time":3.547126241,"remaining_time":3.845084845},
{"learn":[1595.720458],"iteration":250,"passed_time":3.561688174,"remaining_time":3.831298035},
{"learn":[1595.009863],"iteration":251,"passed_time":3.575289945,"remaining_time":3.81648014},
{"learn":[1594.681007],"iteration":252,"passed_time":3.588772805,"remaining_time":3.801545896},
{"learn":[1594.298228],"iteration":253,"passed_time":3.602914823,"remaining_time":3.787315975},
{"learn":[1593.685602],"iteration":254,"passed_time":3.617075091,"remaining_time":3.773105781},
{"learn":[1593.185222],"iteration":255,"passed_time":3.631132658,"remaining_time":3.758789666},
{"learn":[1592.755313],"iteration":256,"passed_time":3.645678731,"remaining_time":3.744977373},
{"learn":[1592.393781],"iteration":257,"passed_time":3.660154813,"remaining_time":3.731088045},
{"learn":[1591.839957],"iteration":258,"passed_time":3.673824825,"remaining_time":3.71637878},
{"learn":[1591.482522],"iteration":259,"passed_time":3.687253484,"remaining_time":3.701435228},
{"learn":[1590.916499],"iteration":260,"passed_time":3.701515114,"remaining_time":3.687333063},
{"learn":[1590.266307],"iteration":261,"passed_time":3.715148285,"remaining_time":3.67260842},
{"learn":[1589.891811],"iteration":262,"passed_time":3.728906929,"remaining_time":3.658015162},
{"learn":[1589.377839],"iteration":263,"passed_time":3.742606251,"remaining_time":3.64337048},
{"learn":[1588.97273],"iteration":264,"passed_time":3.756023221,"remaining_time":3.628460168},
{"learn":[1588.480434],"iteration":265,"passed_time":3.769804094,"remaining_time":3.61390994},
{"learn":[1587.879716],"iteration":266,"passed_time":3.783288464,"remaining_time":3.599083408},
{"learn":[1587.461752],"iteration":267,"passed_time":3.797284021,"remaining_time":3.584749467},
{"learn":[1586.832291],"iteration":268,"passed_time":3.810454867,"remaining_time":3.569645452},
{"learn":[1586.341296],"iteration":269,"passed_time":3.825369334,"remaining_time":3.556176677},
{"learn":[1585.95398],"iteration":270,"passed_time":3.838896325,"remaining_time":3.541417274},
{"learn":[1585.500508],"iteration":271,"passed_time":3.853148504,"remaining_time":3.527330799},
{"learn":[1585.184458],"iteration":272,"passed_time":3.866736505,"remaining_time":3.512639756},
{"learn":[1584.867569],"iteration":273,"passed_time":3.879736109,"remaining_time":3.497426347},
{"learn":[1584.326954],"iteration":274,"passed_time":3.892830405,"remaining_time":3.482313744},
{"learn":[1583.820781],"iteration":275,"passed_time":3.905654047,"remaining_time":3.466975513},
{"learn":[1583.385138],"iteration":276,"passed_time":3.91938122,"remaining_time":3.452451327},
{"learn":[1583.089336],"iteration":277,"passed_time":3.932678088,"remaining_time":3.437556746},
{"learn":[1582.599047],"iteration":278,"passed_time":3.945767963,"remaining_time":3.422494076},
{"learn":[1582.121909],"iteration":279,"passed_time":3.959091101,"remaining_time":3.407646269},
{"learn":[1581.652925],"iteration":280,"passed_time":3.971952804,"remaining_time":3.392415206},
{"learn":[1581.269052],"iteration":281,"passed_time":3.985034819,"remaining_time":3.377387666},
{"learn":[1580.86187],"iteration":282,"passed_time":3.998988555,"remaining_time":3.363106983},
{"learn":[1580.632379],"iteration":283,"passed_time":4.011854538,"remaining_time":3.347920864},
{"learn":[1580.064141],"iteration":284,"passed_time":4.025791883,"remaining_time":3.333638191},
{"learn":[1579.712659],"iteration":285,"passed_time":4.03898565,"remaining_time":3.31874695},
{"learn":[1579.120776],"iteration":286,"passed_time":4.052700343,"remaining_time":3.304292266},
{"learn":[1578.569302],"iteration":287,"passed_time":4.066372665,"remaining_time":3.289808441},
{"learn":[1578.145255],"iteration":288,"passed_time":4.079933476,"remaining_time":3.275240714},
{"learn":[1577.873327],"iteration":289,"passed_time":4.093353295,"remaining_time":3.260567625},
{"learn":[1577.30231],"iteration":290,"passed_time":4.107133249,"remaining_time":3.246187791},
{"learn":[1577.051764],"iteration":291,"passed_time":4.120601099,"remaining_time":3.2315673},
{"learn":[1576.649405],"iteration":292,"passed_time":4.134579085,"remaining_time":3.217351643},
{"learn":[1576.190914],"iteration":293,"passed_time":4.147750501,"remaining_time":3.202514843},
{"learn":[1575.958595],"iteration":294,"passed_time":4.161484894,"remaining_time":3.188120631},
{"learn":[1575.647684],"iteration":295,"passed_time":4.17548083,"remaining_time":3.173929685},
{"learn":[1575.281294],"iteration":296,"passed_time":4.188985481,"remaining_time":3.159369521},
{"learn":[1574.985726],"iteration":297,"passed_time":4.204292212,"remaining_time":3.146164978},
{"learn":[1574.512334],"iteration":298,"passed_time":4.217480089,"remaining_time":3.131373176},
{"learn":[1574.032921],"iteration":299,"passed_time":4.231590567,"remaining_time":3.117271717},
{"learn":[1573.663366],"iteration":300,"passed_time":4.245641153,"remaining_time":3.103126424},
{"learn":[1573.372223],"iteration":301,"passed_time":4.259999394,"remaining_time":3.089204858},
{"learn":[1572.574661],"iteration":302,"passed_time":4.274056121,"remaining_time":3.07506348},
{"learn":[1572.256097],"iteration":303,"passed_time":4.287675432,"remaining_time":3.060610424},
{"learn":[1571.938344],"iteration":304,"passed_time":4.302576949,"remaining_time":3.047070889},
{"learn":[1571.348617],"iteration":305,"passed_time":4.31692583,"remaining_time":3.033134161},
{"learn":[1571.083769],"iteration":306,"passed_time":4.330718583,"remaining_time":3.018807091},
{"learn":[1570.730211],"iteration":307,"passed_time":4.344317605,"remaining_time":3.004349512},
{"learn":[1570.349687],"iteration":308,"passed_time":4.359383854,"remaining_time":2.990904133},
{"learn":[1570.036238],"iteration":309,"passed_time":4.373202948,"remaining_time":2.976599426},
{"learn":[1569.706363],"iteration":310,"passed_time":4.386964251,"remaining_time":2.962258819},
{"learn":[1569.291667],"iteration":311,"passed_time":4.400471021,"remaining_time":2.947751421},
{"learn":[1568.927962],"iteration":312,"passed_time":4.41549975,"remaining_time":2.934261815},
{"learn":[1568.633918],"iteration":313,"passed_time":4.42984424,"remaining_time":2.92031133},
{"learn":[1568.195419],"iteration":314,"passed_time":4.443161318,"remaining_time":2.905686449},
{"learn":[1567.885138],"iteration":315,"passed_time":4.457482558,"remaining_time":2.89172128},
{"learn":[1567.547834],"iteration":316,"passed_time":4.471267602,"remaining_time":2.877408804},
{"learn":[1567.063911],"iteration":317,"passed_time":4.485979457,"remaining_time":2.863691288},
{"learn":[1566.669692],"iteration":318,"passed_time":4.499916342,"remaining_time":2.849476806},
{"learn":[1566.301502],"iteration":319,"passed_time":4.513940909,"remaining_time":2.835319133},
{"learn":[1565.72155],"iteration":320,"passed_time":4.52834245,"remaining_time":2.821397165},
{"learn":[1565.444131],"iteration":321,"passed_time":4.541966641,"remaining_time":2.806991806},
{"learn":[1564.927974],"iteration":322,"passed_time":4.557506496,"remaining_time":2.793765592},
{"learn":[1564.550446],"iteration":323,"passed_time":4.571191158,"remaining_time":2.779397093},
{"learn":[1564.25098],"iteration":324,"passed_time":4.58485961,"remaining_time":2.765023027},
{"learn":[1564.007724],"iteration":325,"passed_time":4.598176169,"remaining_time":2.7504428},
{"learn":[1563.704104],"iteration":326,"passed_time":4.61173462,"remaining_time":2.736013811},
{"learn":[1563.437056],"iteration":327,"passed_time":4.625405652,"remaining_time":2.721656374},
{"learn":[1563.085405],"iteration":328,"passed_time":4.638930122,"remaining_time":2.707217579},
{"learn":[1562.834045],"iteration":329,"passed_time":4.65308007,"remaining_time":2.693146344},
{"learn":[1562.427542],"iteration":330,"passed_time":4.666057764,"remaining_time":2.678401738},
{"learn":[1562.125565],"iteration":331,"passed_time":4.680299114,"remaining_time":2.664387146},
{"learn":[1561.773828],"iteration":332,"passed_time":4.696443575,"remaining_time":2.651445622},
{"learn":[1561.468932],"iteration":333,"passed_time":4.709974826,"remaining_time":2.637021834},
{"learn":[1561.120968],"iteration":334,"passed_time":4.723271114,"remaining_time":2.622472917},
{"learn":[1560.707359],"iteration":335,"passed_time":4.737067307,"remaining_time":2.608206702},
{"learn":[1560.443359],"iteration":336,"passed_time":4.750055112,"remaining_time":2.593501901},
{"learn":[1560.07219],"iteration":337,"passed_time":4.763623393,"remaining_time":2.579121541},
{"learn":[1559.726256],"iteration":338,"passed_time":4.777200624,"remaining_time":2.564750777},
{"learn":[1559.205894],"iteration":339,"passed_time":4.791725706,"remaining_time":2.550889273},
{"learn":[1558.880823],"iteration":340,"passed_time":4.805437659,"remaining_time":2.536594659},
{"learn":[1558.443531],"iteration":341,"passed_time":4.818102889,"remaining_time":2.521755606},
{"learn":[1558.09076],"iteration":342,"passed_time":4.831440038,"remaining_time":2.50727792},
{"learn":[1557.684825],"iteration":343,"passed_time":4.84513011,"remaining_time":2.492988458},
{"learn":[1557.428741],"iteration":344,"passed_time":4.858132175,"remaining_time":2.478351486},
{"learn":[1557.193486],"iteration":345,"passed_time":4.870798265,"remaining_time":2.463554036},
{"learn":[1556.791066],"iteration":346,"passed_time":4.883788719,"remaining_time":2.448931519},
{"learn":[1556.456053],"iteration":347,"passed_time":4.896583931,"remaining_time":2.434221322},
{"learn":[1556.078565],"iteration":348,"passed_time":4.90998095,"remaining_time":2.419818692},
{"learn":[1555.721144],"iteration":349,"passed_time":4.923176187,"remaining_time":2.405323223},
{"learn":[1555.511018],"iteration":350,"passed_time":4.93606561,"remaining_time":2.390687048},
{"learn":[1555.333266],"iteration":351,"passed_time":4.948820441,"remaining_time":2.375996178},
{"learn":[1555.035737],"iteration":352,"passed_time":4.961859826,"remaining_time":2.361451702},
{"learn":[1554.767994],"iteration":353,"passed_time":4.97480314,"remaining_time":2.346870408},
{"learn":[1554.456116],"iteration":354,"passed_time":4.988472002,"remaining_time":2.332637612},
{"learn":[1554.283034],"iteration":355,"passed_time":5.001094312,"remaining_time":2.317922925},
{"learn":[1553.974617],"iteration":356,"passed_time":5.014276768,"remaining_time":2.303477283},
{"learn":[1553.581499],"iteration":357,"passed_time":5.026869038,"remaining_time":2.288769981},
{"learn":[1553.301119],"iteration":358,"passed_time":5.040362368,"remaining_time":2.274481069},
{"learn":[1553.063816],"iteration":359,"passed_time":5.053487754,"remaining_time":2.260032023},
{"learn":[1552.668804],"iteration":360,"passed_time":5.067901185,"remaining_time":2.24616119},
{"learn":[1552.263442],"iteration":361,"passed_time":5.080391693,"remaining_time":2.23144276},
{"learn":[1551.987519],"iteration":362,"passed_time":5.09530283,"remaining_time":2.217790213},
{"learn":[1551.723856],"iteration":363,"passed_time":5.109148115,"remaining_time":2.203671027},
{"learn":[1551.442206],"iteration":364,"passed_time":5.121984597,"remaining_time":2.189122184},
{"learn":[1551.154779],"iteration":365,"passed_time":5.135103503,"remaining_time":2.174702303},
{"learn":[1550.857207],"iteration":366,"passed_time":5.149737027,"remaining_time":2.160925074},
{"learn":[1550.630995],"iteration":367,"passed_time":5.162729971,"remaining_time":2.146461102},
{"learn":[1550.288109],"iteration":368,"passed_time":5.176209361,"remaining_time":2.132205482},
{"learn":[1550.011322],"iteration":369,"passed_time":5.189396367,"remaining_time":2.117834734},
{"learn":[1549.675377],"iteration":370,"passed_time":5.204552127,"remaining_time":2.104266359},
{"learn":[1549.414905],"iteration":371,"passed_time":5.218597634,"remaining_time":2.090244751},
{"learn":[1549.178092],"iteration":372,"passed_time":5.232343687,"remaining_time":2.076104198},
{"learn":[1548.92816],"iteration":373,"passed_time":5.245774667,"remaining_time":2.061841914},
{"learn":[1548.533069],"iteration":374,"passed_time":5.259692132,"remaining_time":2.04777347},
{"learn":[1548.215169],"iteration":375,"passed_time":5.273233893,"remaining_time":2.033560943},
{"learn":[1547.806548],"iteration":376,"passed_time":5.287607943,"remaining_time":2.019669878},
{"learn":[1547.517753],"iteration":377,"passed_time":5.301723511,"remaining_time":2.005678471},
{"learn":[1547.235047],"iteration":378,"passed_time":5.316420285,"remaining_time":1.99190417},
{"learn":[1546.782619],"iteration":379,"passed_time":5.330175459,"remaining_time":1.977775631},
{"learn":[1546.505853],"iteration":380,"passed_time":5.344119194,"remaining_time":1.963718339},
{"learn":[1546.15993],"iteration":381,"passed_time":5.358198001,"remaining_time":1.949710791},
{"learn":[1545.962971],"iteration":382,"passed_time":5.371615241,"remaining_time":1.935464499},
{"learn":[1545.647072],"iteration":383,"passed_time":5.385279413,"remaining_time":1.921310624},
{"learn":[1545.437038],"iteration":384,"passed_time":5.398763713,"remaining_time":1.907095753},
{"learn":[1545.078639],"iteration":385,"passed_time":5.412760999,"remaining_time":1.89306408},
{"learn":[1544.815497],"iteration":386,"passed_time":5.426263529,"remaining_time":1.878861274},
{"learn":[1544.62117],"iteration":387,"passed_time":5.439712899,"remaining_time":1.864643855},
{"learn":[1544.363167],"iteration":388,"passed_time":5.453605664,"remaining_time":1.850580842},
{"learn":[1544.081146],"iteration":389,"passed_time":5.467897074,"remaining_time":1.836652607},
{"learn":[1543.734323],"iteration":390,"passed_time":5.481008789,"remaining_time":1.822330288},
{"learn":[1543.480197],"iteration":391,"passed_time":5.49456652,"remaining_time":1.808160921},
{"learn":[1543.078895],"iteration":392,"passed_time":5.508316734,"remaining_time":1.794057359},
{"learn":[1542.72494],"iteration":393,"passed_time":5.522123537,"remaining_time":1.779973831},
{"learn":[1542.369205],"iteration":394,"passed_time":5.536073333,"remaining_time":1.765937316},
{"learn":[1542.008245],"iteration":395,"passed_time":5.549654054,"remaining_time":1.751784739},
{"learn":[1541.639502],"iteration":396,"passed_time":5.56363936,"remaining_time":1.737761412},
{"learn":[1541.345932],"iteration":397,"passed_time":5.578211443,"remaining_time":1.723919617},
{"learn":[1541.073821],"iteration":398,"passed_time":5.591453221,"remaining_time":1.709667401},
{"learn":[1540.765037],"iteration":399,"passed_time":5.604478575,"remaining_time":1.695354769},
{"learn":[1540.537878],"iteration":400,"passed_time":5.618184398,"remaining_time":1.681252189},
{"learn":[1540.291895],"iteration":401,"passed_time":5.632320606,"remaining_time":1.667278985},
{"learn":[1539.991841],"iteration":402,"passed_time":5.64949774,"remaining_time":1.654195368},
{"learn":[1539.740791],"iteration":403,"passed_time":5.662750767,"remaining_time":1.639955049},
{"learn":[1539.353321],"iteration":404,"passed_time":5.675552899,"remaining_time":1.62559046},
{"learn":[1539.065811],"iteration":405,"passed_time":5.688731735,"remaining_time":1.61134027},
{"learn":[1538.889264],"iteration":406,"passed_time":5.702113064,"remaining_time":1.597152062},
{"learn":[1538.605459],"iteration":407,"passed_time":5.715762736,"remaining_time":1.58304213},
{"learn":[1538.408729],"iteration":408,"passed_time":5.729327327,"remaining_time":1.568911151},
{"learn":[1538.211542],"iteration":409,"passed_time":5.742397063,"remaining_time":1.554648961},
{"learn":[1537.812823],"iteration":410,"passed_time":5.755354306,"remaining_time":1.540362466},
{"learn":[1537.521355],"iteration":411,"passed_time":5.76826923,"remaining_time":1.526071228},
{"learn":[1537.267944],"iteration":412,"passed_time":5.781445086,"remaining_time":1.511854889},
{"learn":[1536.995009],"iteration":413,"passed_time":5.794472131,"remaining_time":1.497605116},
{"learn":[1536.8229],"iteration":414,"passed_time":5.807198852,"remaining_time":1.483284526},
{"learn":[1536.554648],"iteration":415,"passed_time":5.819809742,"remaining_time":1.468942363},
{"learn":[1536.35308],"iteration":416,"passed_time":5.833363732,"remaining_time":1.454843713},
{"learn":[1535.997203],"iteration":417,"passed_time":5.846427428,"remaining_time":1.440626854},
{"learn":[1535.746704],"iteration":418,"passed_time":5.859881737,"remaining_time":1.42651059},
{"learn":[1535.450005],"iteration":419,"passed_time":5.873651521,"remaining_time":1.412473342},
{"learn":[1535.099056],"iteration":420,"passed_time":5.886740646,"remaining_time":1.398275688},
{"learn":[1534.87112],"iteration":421,"passed_time":5.899990143,"remaining_time":1.38412091},
{"learn":[1534.551258],"iteration":422,"passed_time":5.914311523,"remaining_time":1.370218745},
{"learn":[1534.279953],"iteration":423,"passed_time":5.927187066,"remaining_time":1.355983834},
{"learn":[1534.060531],"iteration":424,"passed_time":5.940753087,"remaining_time":1.341911286},
{"learn":[1533.846812],"iteration":425,"passed_time":5.955375901,"remaining_time":1.328076785},
{"learn":[1533.534155],"iteration":426,"passed_time":5.9696496,"remaining_time":1.314161739},
{"learn":[1533.069497],"iteration":427,"passed_time":5.984476376,"remaining_time":1.300365194},
{"learn":[1532.744812],"iteration":428,"passed_time":5.998460202,"remaining_time":1.286383074},
{"learn":[1532.602392],"iteration":429,"passed_time":6.014487113,"remaining_time":1.272833319},
{"learn":[1532.366466],"iteration":430,"passed_time":6.028721062,"remaining_time":1.258897669},
{"learn":[1532.172245],"iteration":431,"passed_time":6.043495987,"remaining_time":1.24507209},
{"learn":[1531.836486],"iteration":432,"passed_time":6.057464123,"remaining_time":1.231078159},
{"learn":[1531.490368],"iteration":433,"passed_time":6.072997537,"remaining_time":1.217398124},
{"learn":[1531.279752],"iteration":434,"passed_time":6.087669492,"remaining_time":1.203539256},
{"learn":[1530.980419],"iteration":435,"passed_time":6.101241453,"remaining_time":1.18946221},
{"learn":[1530.754011],"iteration":436,"passed_time":6.115106127,"remaining_time":1.175443741},
{"learn":[1530.436126],"iteration":437,"passed_time":6.129731501,"remaining_time":1.161570125},
{"learn":[1530.122572],"iteration":438,"passed_time":6.144078281,"remaining_time":1.147641046},
{"learn":[1529.82803],"iteration":439,"passed_time":6.158502492,"remaining_time":1.133724322},
{"learn":[1529.537093],"iteration":440,"passed_time":6.173262678,"remaining_time":1.119866245},
{"learn":[1529.364621],"iteration":441,"passed_time":6.188527629,"remaining_time":1.106094305},
{"learn":[1528.935773],"iteration":442,"passed_time":6.203072102,"remaining_time":1.092188767},
{"learn":[1528.705405],"iteration":443,"passed_time":6.217607444,"remaining_time":1.078278768},
{"learn":[1528.433732],"iteration":444,"passed_time":6.231254196,"remaining_time":1.0642142},
{"learn":[1528.159779],"iteration":445,"passed_time":6.244818087,"remaining_time":1.050137571},
{"learn":[1527.781865],"iteration":446,"passed_time":6.258878784,"remaining_time":1.036145481},
{"learn":[1527.469149],"iteration":447,"passed_time":6.273374636,"remaining_time":1.022223992},
{"learn":[1527.242004],"iteration":448,"passed_time":6.287433683,"remaining_time":1.0082299},
{"learn":[1526.980186],"iteration":449,"passed_time":6.302982108,"remaining_time":0.9944705103},
{"learn":[1526.680933],"iteration":450,"passed_time":6.317452649,"remaining_time":0.9805358879},
{"learn":[1526.473743],"iteration":451,"passed_time":6.331456846,"remaining_time":0.9665277043},
{"learn":[1526.188936],"iteration":452,"passed_time":6.345373961,"remaining_time":0.9525064665},
{"learn":[1525.944076],"iteration":453,"passed_time":6.359127064,"remaining_time":0.938461483},
{"learn":[1525.752002],"iteration":454,"passed_time":6.373710767,"remaining_time":0.9245382652},
{"learn":[1525.21305],"iteration":455,"passed_time":6.388366041,"remaining_time":0.9106223524},
{"learn":[1524.955572],"iteration":456,"passed_time":6.401948453,"remaining_time":0.8965529562},
{"learn":[1524.66767],"iteration":457,"passed_time":6.416631687,"remaining_time":0.8826371098},
{"learn":[1524.389936],"iteration":458,"passed_time":6.430768785,"remaining_time":0.8686441496},
{"learn":[1524.200091],"iteration":459,"passed_time":6.444504288,"remaining_time":0.8545973077},
{"learn":[1523.914953],"iteration":460,"passed_time":6.458057029,"remaining_time":0.8405280298},
{"learn":[1523.723725],"iteration":461,"passed_time":6.472174346,"remaining_time":0.8265330875},
{"learn":[1523.379713],"iteration":462,"passed_time":6.486279434,"remaining_time":0.8125360846},
{"learn":[1523.082661],"iteration":463,"passed_time":6.501691357,"remaining_time":0.7986991537},
{"learn":[1522.750084],"iteration":464,"passed_time":6.51625746,"remaining_time":0.7847535865},
{"learn":[1522.537547],"iteration":465,"passed_time":6.52977719,"remaining_time":0.7706818572},
{"learn":[1522.336922],"iteration":466,"passed_time":6.543713936,"remaining_time":0.756660712},
{"learn":[1522.135435],"iteration":467,"passed_time":6.557161945,"remaining_time":0.7425845793},
{"learn":[1521.826507],"iteration":468,"passed_time":6.570696836,"remaining_time":0.7285207579},
{"learn":[1521.561413],"iteration":469,"passed_time":6.584017634,"remaining_time":0.714435956},
{"learn":[1521.361507],"iteration":470,"passed_time":6.598092781,"remaining_time":0.7004344778},
{"learn":[1521.140854],"iteration":471,"passed_time":6.612111078,"remaining_time":0.6864267856},
{"learn":[1520.935025],"iteration":472,"passed_time":6.626191135,"remaining_time":0.672425316},
{"learn":[1520.758732],"iteration":473,"passed_time":6.639637864,"remaining_time":0.6583607165},
{"learn":[1520.600088],"iteration":474,"passed_time":6.65354942,"remaining_time":0.6443437333},
{"learn":[1520.404304],"iteration":475,"passed_time":6.666656505,"remaining_time":0.6302511402},
{"learn":[1520.076752],"iteration":476,"passed_time":6.6805262,"remaining_time":0.6162330247},
{"learn":[1519.912738],"iteration":477,"passed_time":6.694176092,"remaining_time":0.6021957572},
{"learn":[1519.699859],"iteration":478,"passed_time":6.707419779,"remaining_time":0.58812449},
{"learn":[1519.525277],"iteration":479,"passed_time":6.720923679,"remaining_time":0.5740788976},
{"learn":[1519.31742],"iteration":480,"passed_time":6.734842105,"remaining_time":0.5600700295},
{"learn":[1519.07478],"iteration":481,"passed_time":6.747667157,"remaining_time":0.5459730687},
{"learn":[1518.806239],"iteration":482,"passed_time":6.761261568,"remaining_time":0.5319419039},
{"learn":[1518.627396],"iteration":483,"passed_time":6.774765589,"remaining_time":0.5179056338},
{"learn":[1518.433724],"iteration":484,"passed_time":6.787628591,"remaining_time":0.5038239779},
{"learn":[1518.232148],"iteration":485,"passed_time":6.801352794,"remaining_time":0.4898093576},
{"learn":[1517.964275],"iteration":486,"passed_time":6.815032727,"remaining_time":0.4757928392},
{"learn":[1517.723071],"iteration":487,"passed_time":6.828647048,"remaining_time":0.4617732635},
{"learn":[1517.566271],"iteration":488,"passed_time":6.841816995,"remaining_time":0.4477262655},
{"learn":[1517.246218],"iteration":489,"passed_time":6.85494676,"remaining_time":0.4336803053},
{"learn":[1516.945017],"iteration":490,"passed_time":6.869130329,"remaining_time":0.4197024641},
{"learn":[1516.762856],"iteration":491,"passed_time":6.88273453,"remaining_time":0.405689637},
{"learn":[1516.592003],"iteration":492,"passed_time":6.897464125,"remaining_time":0.3917423844},
{"learn":[1516.446729],"iteration":493,"passed_time":6.911691504,"remaining_time":0.3777645154},
{"learn":[1516.266237],"iteration":494,"passed_time":6.926078705,"remaining_time":0.363794033},
{"learn":[1515.957437],"iteration":495,"passed_time":6.939622456,"remaining_time":0.3497793576},
{"learn":[1515.676856],"iteration":496,"passed_time":6.954202479,"remaining_time":0.3358166187},
{"learn":[1515.34238],"iteration":497,"passed_time":6.96942753,"remaining_time":0.3218811911},
{"learn":[1515.123238],"iteration":498,"passed_time":6.98374588,"remaining_time":0.3079006199},
{"learn":[1514.917155],"iteration":499,"passed_time":6.997097178,"remaining_time":0.2938780815},
{"learn":[1514.725699],"iteration":500,"passed_time":7.011230336,"remaining_time":0.2798894346},
{"learn":[1514.452465],"iteration":501,"passed_time":7.025199192,"remaining_time":0.2658939933},
{"learn":[1514.310665],"iteration":502,"passed_time":7.039623383,"remaining_time":0.2519149521},
{"learn":[1514.097475],"iteration":503,"passed_time":7.053131353,"remaining_time":0.2379032401},
{"learn":[1513.866139],"iteration":504,"passed_time":7.06803501,"remaining_time":0.2239377429},
{"learn":[1513.614081],"iteration":505,"passed_time":7.082171198,"remaining_time":0.2099457865},
{"learn":[1513.353306],"iteration":506,"passed_time":7.09585357,"remaining_time":0.1959407298},
{"learn":[1512.868069],"iteration":507,"passed_time":7.111036291,"remaining_time":0.1819753381},
{"learn":[1512.667022],"iteration":508,"passed_time":7.125235009,"remaining_time":0.1679819649},
{"learn":[1512.325398],"iteration":509,"passed_time":7.139022913,"remaining_time":0.1539789256},
{"learn":[1512.091412],"iteration":510,"passed_time":7.152905618,"remaining_time":0.1399785835},
{"learn":[1511.854852],"iteration":511,"passed_time":7.16739653,"remaining_time":0.1259893921},
{"learn":[1511.504067],"iteration":512,"passed_time":7.181513227,"remaining_time":0.111992409},
{"learn":[1511.190137],"iteration":513,"passed_time":7.194805905,"remaining_time":0.09798373801},
{"learn":[1510.938083],"iteration":514,"passed_time":7.209410639,"remaining_time":0.08399313365},
{"learn":[1510.769783],"iteration":515,"passed_time":7.222687246,"remaining_time":0.06998727952},
{"learn":[1510.447994],"iteration":516,"passed_time":7.2373662,"remaining_time":0.05599509633},
{"learn":[1510.237868],"iteration":517,"passed_time":7.252154486,"remaining_time":0.04200089471},
{"learn":[1510.0657],"iteration":518,"passed_time":7.266305094,"remaining_time":0.0280011757},
{"learn":[1509.935121],"iteration":519,"passed_time":7.279917066,"remaining_time":0.01399984051},
{"learn":[1509.678411],"iteration":520,"passed_time":7.293514107,"remaining_time":0}
]}